{
  "display": {
    "title": "METATOKYO5",
    "favicon": "favicon_asset",
    "navmapThumbnail": "scene-thumbnail.png"
  },
  "owner": "",
  "contact": {
    "name": "author-name",
    "email": ""
  },
  "main": "bin/game.js",
  "tags": [],
  "scene": {
    "parcels": [
      "0,0"
    ],
    "base": "0,0"
  },
  "source": {
    "version": 1,
    "origin": "builder",
    "projectId": "65f9e304-d2c1-44cd-84e6-4a67c549feea",
    "point": {
      "x": 0,
      "y": 0
    },
    "rotation": "east",
    "layout": {
      "rows": 1,
      "cols": 1
    }
  }
}